__init__.py
cod_plugin.py
pdf_generator.py
promium_plugin.py
cod_plugins-0.0.1.dist-info/METADATA
cod_plugins-0.0.1.dist-info/WHEEL
cod_plugins-0.0.1.dist-info/top_level.txt
cod_plugins-0.0.1.dist-info/RECORD
